bike4py/auth.py
bike4py/cli.py
bike4py/client.py
bike4py/config.py
bike4py/exceptions.py
bike4py/models.py
bike4py-0.1.1.dist-info/METADATA
bike4py-0.1.1.dist-info/WHEEL
bike4py-0.1.1.dist-info/entry_points.txt
bike4py-0.1.1.dist-info/licenses/LICENSE
bike4py-0.1.1.dist-info/RECORD
