Metadata-Version: 2.4
Name: bike4py
Version: 0.1.1
Summary: Bike4Mind API client
Project-URL: Homepage, https://bike4mind.com
Project-URL: Repository, https://github.com/MillionOnMars/bike4py
License-Expression: MIT
License-File: LICENSE
Keywords: api,bike4mind,bike4py,chat,client,llm
Classifier: Operating System :: OS Independent
Classifier: Programming Language :: Python :: 3
Requires-Python: >=3.8
Requires-Dist: aiohttp>=3.9.0
Requires-Dist: click>=8.0.0
Requires-Dist: httpx>=0.24.0
Requires-Dist: pydantic>=2.0
Requires-Dist: websockets>=11.0
Provides-Extra: dev
Requires-Dist: black>=23.0; extra == 'dev'
Requires-Dist: mypy>=1.0; extra == 'dev'
Requires-Dist: pytest-asyncio>=0.21.0; extra == 'dev'
Requires-Dist: pytest>=7.0; extra == 'dev'
